mypkghk/__init__.py
mypkghk-0.1.dist-info/LICENSE.txt
mypkghk-0.1.dist-info/METADATA
mypkghk-0.1.dist-info/WHEEL
mypkghk-0.1.dist-info/top_level.txt
mypkghk-0.1.dist-info/RECORD
