Metadata-Version: 2.1
Name: mypkghk
Version: 0.1
Summary: This is basic code for learn package
Author: Hardik Kanak
Author-email: hardik.kanak@softqubes.com
Classifier: Programming Language :: Python :: 3
Classifier: License :: OSI Approved :: MIT License
Classifier: Operating System :: OS Independent
License-File: LICENSE.txt
